awsm/__init__.py
awsm/data/__init__.py
awsm/data/init_model.py
awsm/framework/CoreConfig.ini
awsm/framework/__init__.py
awsm/framework/ascii_art.py
awsm/framework/changelog.ini
awsm/framework/framework.py
awsm/framework/recipes.ini
awsm/interface/__init__.py
awsm/interface/ingest_data.py
awsm/interface/initialize_model.py
awsm/interface/interface.py
awsm/interface/ipysnobal.py
awsm/interface/pysnobal_io.py
awsm/interface/smrf_ipysnobal.py
awsm/tests/__init__.py
awsm/tests/awsm_test_case.py
awsm/tests/awsm_test_case_lakes.py
awsm/tests/test_awsm_lakes.py
awsm/tests/test_awsm_lakes_init.py
awsm/tests/test_awsm_lakes_lidar_update.py
awsm/tests/test_awsm_rme.py
awsm/tests/test_model_rme.py
awsm/tests/basins/Lakes/config.ini
awsm/tests/basins/Lakes/gold_hrrr/em.nc
awsm/tests/basins/Lakes/gold_hrrr/gold_config.ini
awsm/tests/basins/Lakes/gold_hrrr/make_gold_hrrr
awsm/tests/basins/Lakes/gold_hrrr/snow.nc
awsm/tests/basins/Lakes/gold_hrrr_update/em.nc
awsm/tests/basins/Lakes/gold_hrrr_update/gold_config.ini
awsm/tests/basins/Lakes/gold_hrrr_update/make_gold_hrrr_update
awsm/tests/basins/Lakes/gold_hrrr_update/model_lidar_change.nc
awsm/tests/basins/Lakes/gold_hrrr_update/snow.nc
awsm/tests/basins/Lakes/input/make_Lakes_input
awsm/tests/basins/Lakes/input/data20191001/wind_ninja_data/topo_windninja_topo_10-01-2019_1400_200m_ang.asc
awsm/tests/basins/Lakes/input/data20191001/wind_ninja_data/topo_windninja_topo_10-01-2019_1400_200m_ang.prj
awsm/tests/basins/Lakes/input/data20191001/wind_ninja_data/topo_windninja_topo_10-01-2019_1400_200m_vel.asc
awsm/tests/basins/Lakes/input/data20191001/wind_ninja_data/topo_windninja_topo_10-01-2019_1400_200m_vel.prj
awsm/tests/basins/Lakes/input/data20191001/wind_ninja_data/topo_windninja_topo_10-01-2019_1500_200m_ang.asc
awsm/tests/basins/Lakes/input/data20191001/wind_ninja_data/topo_windninja_topo_10-01-2019_1500_200m_ang.prj
awsm/tests/basins/Lakes/input/data20191001/wind_ninja_data/topo_windninja_topo_10-01-2019_1500_200m_vel.asc
awsm-0.11.2.dist-info/AUTHORS.rst
awsm-0.11.2.dist-info/LICENSE.md
awsm-0.11.2.dist-info/METADATA
awsm-0.11.2.dist-info/WHEEL
awsm-0.11.2.dist-info/top_level.txt
awsm-0.11.2.dist-info/RECORD
