Metadata-Version: 2.1
Name: awsm
Version: 0.11.2
Summary: Automated Water Supply Model
Home-page: https://github.com/USDA-ARS-NWRC/awsm
Author: USDA ARS Northwest Watershed Research Center
Author-email: snow@ars.usda.gov
License: CC0 1.0
Keywords: awsm
Platform: UNKNOWN
Classifier: Development Status :: 2 - Pre-Alpha
Classifier: Intended Audience :: Developers
Classifier: License :: CC0 1.0 Universal (CC0 1.0) Public Domain Dedication
Classifier: Natural Language :: English
Classifier: Programming Language :: Python :: 3.6
Classifier: Programming Language :: Python :: 3.7
Classifier: Programming Language :: Python :: 3.8
Requires-Python: >3.5
Requires-Dist: cftime (==1.1.2)
Requires-Dist: smrf-dev (!=0.11.1,<0.12.0,>=0.11.0)
Requires-Dist: setuptools-scm (<4.2)
